coverage_config_reload_plugin.py
coverage_config_reload_plugin-0.3.0.dist-info/LICENSE
coverage_config_reload_plugin-0.3.0.dist-info/METADATA
coverage_config_reload_plugin-0.3.0.dist-info/WHEEL
coverage_config_reload_plugin-0.3.0.dist-info/top_level.txt
coverage_config_reload_plugin-0.3.0.dist-info/RECORD
