Metadata-Version: 2.1
Name: coverage-config-reload-plugin
Version: 0.3.0
Summary: coverage.py config reload plugin
Home-page: https://github.com/jayvdb/coverage_config_reload_plugin
Author: John Vandenberg
Author-email: jayvdb@gmail.com
License: MIT License
Platform: UNKNOWN
Classifier: Environment :: Console
Classifier: Intended Audience :: Developers
Classifier: License :: OSI Approved :: MIT License
Classifier: Operating System :: OS Independent
Classifier: Programming Language :: Python :: 2.7
Classifier: Programming Language :: Python :: 3.4
Classifier: Programming Language :: Python :: 3.5
Classifier: Programming Language :: Python :: 3.6
Classifier: Programming Language :: Python :: 3.7
Classifier: Programming Language :: Python :: Implementation :: CPython
Classifier: Programming Language :: Python :: Implementation :: PyPy
Classifier: Topic :: Software Development :: Quality Assurance
Classifier: Topic :: Software Development :: Testing
Classifier: Development Status :: 4 - Beta
Requires-Dist: coverage (>=4.0)
